message/__init__.py
message/plugin.py
sentry_message_plugin-2.3.dist-info/LICENSE
sentry_message_plugin-2.3.dist-info/METADATA
sentry_message_plugin-2.3.dist-info/WHEEL
sentry_message_plugin-2.3.dist-info/entry_points.txt
sentry_message_plugin-2.3.dist-info/top_level.txt
sentry_message_plugin-2.3.dist-info/RECORD
